README.md
setup.cfg
setup.py
yaledining/__init__.py
yaledining/main.py
yaledining/models.py
yaledining.egg-info/PKG-INFO
yaledining.egg-info/SOURCES.txt
yaledining.egg-info/dependency_links.txt
yaledining.egg-info/requires.txt
yaledining.egg-info/top_level.txt