Metadata-Version: 1.0
Name: yaledining
Version: 1.1.0
Summary: Library for abstractly fetching data from the Yale Dining API.
Home-page: https://github.com/ErikBoesen/yaledining
Author: Erik Boesen
Author-email: me@erikboesen.com
License: GPL
Platform: UNKNOWN
